combojsonapi/__init__.py
combojsonapi/event/__init__.py
combojsonapi/event/plugin.py
combojsonapi/event/resource.py
combojsonapi/permission/__init__.py
combojsonapi/permission/exceptions.py
combojsonapi/permission/permission_plugin.py
combojsonapi/permission/permission_system.py
combojsonapi/postgresql_jsonb/__init__.py
combojsonapi/postgresql_jsonb/plugin.py
combojsonapi/postgresql_jsonb/schema.py
combojsonapi/spec/__init__.py
combojsonapi/spec/compat.py
combojsonapi/spec/plugin.py
combojsonapi/spec/plugins_for_apispec.py
combojsonapi/spec/apispec/__init__.py
combojsonapi/spec/apispec/plugins.py
combojsonapi/spec/apispec/templates/redoc.html
combojsonapi/spec/apispec/templates/swagger_ui.html
combojsonapi/utils/__init__.py
combojsonapi/utils/decorators.py
combojsonapi/utils/http_status.py
combojsonapi/utils/marshmallow_fields.py
combojsonapi/utils/schema_name.py
tests/test_event/__init__.py
tests/test_event/test_plugin.py
tests/test_permission/__init__.py
tests/test_permission/test_permission_plugin.py
tests/test_permission/test_permission_system.py
tests/test_postgresql_jsonb/__init__.py
tests/test_postgresql_jsonb/test_plugin.py
tests/test_spec/__init__.py
tests/test_spec/test_plugin.py
tests/test_spec/test_plugins_for_apispec.py
tests/test_utils/__init__.py
tests/test_utils/test_decorators.py
tests/test_utils/test_marshmallow_fields.py
tests/test_utils/test_schema_name.py
ComboJSONAPI-1.1.2.dist-info/LICENSE
ComboJSONAPI-1.1.2.dist-info/METADATA
ComboJSONAPI-1.1.2.dist-info/WHEEL
ComboJSONAPI-1.1.2.dist-info/top_level.txt
ComboJSONAPI-1.1.2.dist-info/RECORD
